{
    "1": {
        "question": "下列哪个选项最准确地描述了连接主义（Connectionism）？",
        "options": {
            "A": "连接主义认为认知过程可以通过明确的符号系统进行推理，类似于传统的符号主义。",
            "B": "连接主义专注于将智能归结为生物神经元网络的简化模型，模拟生物学习过程。",
            "C": "连接主义模型由大量简单的处理单元组成的网络，能够进行分布式信息处理和自适应学习。",
            "D": "连接主义认为智能的核心在于符号计算，并通过逻辑推理实现复杂的任务。"
        },
        "correct": "C",
        "explanation": "连接主义的核心在于模拟生物神经网络的工作机制，使用由大量简单单元组成的网络进行非线性和分布式的处理。选项 c 准确描述了连接主义的特征，而其他选项更多反映了符号主义或对连接主义的误解。"
    },
    "2": {
        "question": "关于表示学习（Representation Learning），以下哪种说法是正确的？",
        "options": {
            "A": "表示学习的核心是从数据中提取特征，而不必关注特征的语义意义。",
            "B": "表示学习的主要挑战是从低级特征中自动学习到可以解决高级任务的语义表示。",
            "C": "局部表示通常优于分布式表示，因为局部表示更易于进行模型解释。",
            "D": "表示学习主要依赖于通过手工设计特征来提高模型性能。"
        },
        "correct": "B",
        "explanation": "表示学习的目标是自动发现适合于特定任务的有效表示形式，尤其是通过从原始数据中学习出具有语义含义的高层特征。解决“语义鸿沟”问题是表示学习的关键挑战，因此选项 b 是正确的，而其他选项则或忽略了自动学习的能力，或对表示学习的目的有所误解。"
    },
    "3": {
        "question": "在人工智能的发展历程中，以下哪个时期被认为是专注于通过构建知识库来提升智能系统的？",
        "options": {
            "A": "推理期，该时期通过符号推理来模拟人类逻辑能力，忽略了对知识的积累。",
            "B": "学习期，强调机器从数据中自动学习，但尚未发展知识库的概念。",
            "C": "知识期，此阶段强调了知识对于构建智能系统的重要性，专家系统便是在此基础上诞生的。",
            "D": "智能期，该时期机器开始通过大数据和深度学习模型来构建复杂的知识系统。"
        },
        "correct": "C",
        "explanation": "知识期是人工智能发展的重要阶段，研究者认识到构建知识库的重要性，并致力于将领域知识融入智能系统，以提升其决策和推理能力。专家系统是该时期的代表性成果，选项 c 正确地捕捉了这一关键发展。"
    }
}
